{
	"format_version": "1.12.0",
	"minecraft:geometry": [
		{
			"description": {
				"identifier": "geometry.protogen",
				"texture_width": 128,
				"texture_height": 128,
				"visible_bounds_width": 3,
				"visible_bounds_height": 3.5,
				"visible_bounds_offset": [0, 1.25, 0]
			},
			"bones": [
				{
					"name": "head",
					"pivot": [0, 25, 0],
					"cubes": [
						{"origin": [-3.60378, 25.23286, -1.67302], "size": [1, 5, 1], "pivot": [-3, 26, -2], "rotation": [0.83705, -12.17335, 7.68322], "uv": [44, 60]},
						{"origin": [-3.45949, 23.85593, -2.11476], "size": [0, 4, 5], "pivot": [0, 28, -1], "rotation": [0.29712, -12.1981, 10.24073], "uv": [32, 3]},
						{"origin": [11.31313, 15.07485, -1.14523], "size": [1, 6, 1], "pivot": [0, 18, -2], "rotation": [-0.531, 2.3889, -89.47706], "uv": [16, 45]},
						{"origin": [2.38034, 24.85947, -1.24404], "size": [1, 5, 1], "pivot": [0, 28, -1], "rotation": [-0.40648, 9.78237, -5.53071], "uv": [48, 35]},
						{"origin": [3.38034, 23.85947, -2.24404], "size": [0, 4, 5], "pivot": [0, 28, -1], "rotation": [-0.83694, 9.75524, -8.06735], "uv": [20, 24]},
						{"origin": [-2, 26, 1], "size": [0, 1, 4], "pivot": [0, 24, -5], "rotation": [2.5, -7.5, 0], "uv": [0, 0]},
						{"origin": [-2, 28, 6], "size": [0, 3, 1], "pivot": [0, 24, -5], "rotation": [2.5, -7.5, 0], "uv": [0, 0]},
						{"origin": [2, 26, 1], "size": [0, 1, 4], "pivot": [0, 24, -5], "rotation": [2.5, 7.5, 0], "uv": [0, 1]},
						{"origin": [2, 28, 6], "size": [0, 3, 1], "pivot": [0, 24, -5], "rotation": [2.5, 7.5, 0], "uv": [2, 0]},
						{"origin": [-3, 27, 1], "size": [2, 2, 8], "pivot": [0, 24, -5], "rotation": [17.79767, -6.74193, -2.40084], "uv": [68, 72]},
						{"origin": [1, 27, 1], "size": [2, 2, 8], "pivot": [0, 24, -5], "rotation": [17.79767, 6.74193, 2.40084], "uv": [76, 0]},
						{"origin": [2, 27, 1], "size": [0, 3, 5], "pivot": [0, 24, -5], "rotation": [2.5, 7.5, 0], "uv": [42, 27]},
						{"origin": [-2, 27, 1], "size": [0, 3, 5], "pivot": [0, 24, -5], "rotation": [2.5, -7.5, 0], "uv": [40, 52]},
						{"origin": [-3, 26, -1], "size": [6, 5, 3], "uv": [24, 0]},
						{"origin": [-2.43875, 25, -5.07294], "size": [1, 5, 7], "pivot": [0, 29, -3], "rotation": [0, -10, 0], "uv": [29, 77]},
						{"origin": [0.9178, 25, -5.11852], "size": [1, 5, 7], "pivot": [0, 30, -6], "rotation": [0, 10, 0], "uv": [77, 57]},
						{"origin": [-2, 25, -6], "size": [4, 5, 1], "uv": [0, 61]},
						{"origin": [-2, 25.001, -5], "size": [4, 5, 6], "uv": [16, 73]}
					]
				},
				{
					"name": "rightArm",
					"pivot": [-5, 22, 0],
					"cubes": [
						{"origin": [-8, 12, -2], "size": [4, 12, 4], "uv": [48, 16]},
						{"origin": [-8, 12, -2], "size": [4, 12, 4], "inflate": 0.1, "uv": [0, 45]}
					]
				},
				{
					"name": "leftArm",
					"pivot": [5, 22, 0],
					"cubes": [
						{"origin": [4, 12, -2], "size": [4, 12, 4], "uv": [52, 32]},
						{"origin": [4, 12, -2], "size": [4, 12, 4], "inflate": 0.1, "uv": [44, 0]}
					]
				},
				{
					"name": "rightLeg",
					"pivot": [-2, 12, 0],
					"cubes": [
						{"origin": [-4, 0, -2], "size": [4, 12, 4], "uv": [12, 57]},
						{"origin": [-4.1, 0, -2], "size": [4, 12, 4], "inflate": 0.1, "uv": [60, 0]}
					]
				},
				{
					"name": "leftLeg",
					"pivot": [2, 12, 0],
					"cubes": [
						{"origin": [0, 0, -2], "size": [4, 12, 4], "uv": [52, 48]},
						{"origin": [0.1, 0, -2], "size": [4, 12, 4], "inflate": 0.1, "uv": [20, 41]}
					]
				},
				{
					"name": "torso",
					"pivot": [0, 0, 0],
					"cubes": [
						{"origin": [-4, 12, -2], "size": [8, 12, 4], "uv": [24, 13]},
						{"origin": [-4, 12, -2], "size": [8, 12, 4], "inflate": 0.25, "uv": [0, 13]},
						{"origin": [0, 20, 0], "size": [8, 5, 8], "pivot": [0, 0, 0], "rotation": [18.94528, -41.28047, -13.33431], "uv": [0, 0]}
					]
				},
				{
					"name": "tail",
					"pivot": [0, 0, 0]
				}
			]
		}
	]
}